django_template_admin_urls-0.1.3.dist-info/dependency_links.txt
django_template_admin_urls-0.1.3.dist-info/entry_points.txt
django_template_admin_urls-0.1.3.dist-info/METADATA
django_template_admin_urls-0.1.3.dist-info/top_level.txt
django_template_admin_urls-0.1.3.dist-info/WHEEL
dj_template_admin_urls/__init__.py
dj_template_admin_urls/templatetags/admin_links.py
dj_template_admin_urls/templatetags/__init__.py
dj_template_admin_urls/templates/admin_links.jinja
django_template_admin_urls-0.1.3.dist-info/LICENSE
django_template_admin_urls-0.1.3.dist-info/AUTHORS
django_template_admin_urls-0.1.3.dist-info/RECORD